{
  "{asid}": {
    "profileList": ["AsidAuthorities", "AsidExecutives", "AsidLicenseOwner", "Public"],
    "useCaseMap": {}
  },
  "*": {
    "profileList": ["Authorities", "Executives", "AwidLicenseOwner", "Public", "Readers", "yes"],
    "useCaseMap": {
      "sys/uuAppWorkspace/init": {
        "sysStateList": ["created"],
        "profileList": ["AwidLicenseOwner"]
      },
      "defaultUve": {
        "profileList": ["Public"]
      },
      "sys/uuAppWorkspace/initUve": {
        "sysStateList": ["created"],
        "profileList": ["Public", "AwidLicenseOwner"]
      },
      "sayHello": {
        "sysStateList": ["active"],
        "profileList": ["Public"]
      },
      "subject/create": {
        "sysStateList": ["active"],
        "profileList": ["Authorities", "Readers", "Executives"]
      },
      "programme/create": {
        "sysStateList": ["active"],
        "profileList": ["Authorities", "Readers", "Executives"]
      },
      "subject/update": {
        "sysStateList": ["active"],
        "profileList": ["Authorities"]
      },
      "subject/get": {
        "sysStateList": ["active"],
        "profileList": ["Authorities"]
      },
      "subject/remove": {
        "sysStateList": ["active"],
        "profileList": ["Authorities"]
      },
      "subject/list": {
        "sysStateList": ["active"],
        "profileList": ["Authorities", "Readers", "Executives", "Public"]
      },
      "programme/get": {
        "sysStateList": ["active"],
        "profileList": ["Authorities"]
      },
      "programme/update": {
        "sysStateList": ["active"],
        "profileList": ["Authorities"]
      },
      "programme/list": {
        "sysStateList": ["active"],
        "profileList": ["Authorities"]
      },
      "programme/remove": {
        "sysStateList": ["active"],
        "profileList": ["Authorities"]
      },
      "topic/create": {
        "sysStateList": ["active"],
        "profileList": ["Authorities", "Executives"]
      },
      "topic/get": {
        "sysStateList": ["active"],
        "profileList": ["Authorities"]
      },
      "topic/update": {
        "sysStateList": ["active"],
        "profileList": ["Authorities"]
      },
      "topic/list": {
        "sysStateList": ["active"],
        "profileList": ["Authorities"]
      },
      "topic/remove": {
        "sysStateList": ["active"],
        "profileList": ["Authorities"]
      }
    }
  }
}
